[
    {
        "createDate": "12/27/2020",
        "epicReferralID": "123",
        "memberFName": "Ian",
        "memberLName": "Harry",
        "reqProvSpec": "4",
        "reqProvSpecDesc": "Cardiology",
        "memberMRN": "111111"
    },
    {
        "createDate": "12/27/2020",
        "epicReferralID": "TEST 10",
        "memberFName": "Ian",
        "memberLName": "Harry",
        "reqProvSpec": "4",
        "reqProvSpecDesc": "Cardiology",
        "memberMRN": "111111"
    },
    {
        "createDate": "12/27/2020",
        "epicReferralID": "HI THERE",
        "memberFName": "Ian",
        "memberLName": "Harry",
        "reqProvSpec": "4",
        "reqProvSpecDesc": "Cardiology",
        "memberMRN": "111111"
    },
    {
        "createDate": "12/27/2020",
        "epicReferralID": "4342",
        "memberFName": "Larry",
        "memberLName": "Harry",
        "reqProvSpec": "4",
        "reqProvSpecDesc": "Cardiology",
        "memberMRN": "222222"
    },
    {
        "createDate": "12/27/2020",
        "epicReferralID": "76576",
        "memberFName": "Larry",
        "memberLName": "Harry",
        "reqProvSpec": "4",
        "reqProvSpecDesc": "Cardiology",
        "memberMRN": "222222"
    }
]